.gitignore
LICENSE.txt
README.rst
setup.py
zerokspot/__init__.py
zerokspot.recipe.distutils.egg-info/PKG-INFO
zerokspot.recipe.distutils.egg-info/SOURCES.txt
zerokspot.recipe.distutils.egg-info/dependency_links.txt
zerokspot.recipe.distutils.egg-info/entry_points.txt
zerokspot.recipe.distutils.egg-info/namespace_packages.txt
zerokspot.recipe.distutils.egg-info/requires.txt
zerokspot.recipe.distutils.egg-info/top_level.txt
zerokspot.recipe.distutils.egg-info/zip-safe
zerokspot/recipe/__init__.py
zerokspot/recipe/distutils/__init__.py