Metadata-Version: 1.0
Name: zerokspot.recipe.distutils
Version: 0.1.2
Summary: Recipe for zc.buildout that downloads one or multiple distutils-archives and installs them
Home-page: http://github.com/zerok/zerokspot.recipe.distutils/
Author: Horst Gutmann
Author-email: zerok@zerokspot.com
License: UNKNOWN
Platform: UNKNOWN
Classifier: Development Status :: 3 - Alpha
Classifier: Environment :: Plugins
Classifier: Framework :: Buildout
Classifier: Intended Audience :: Developers
Classifier: Programming Language :: Python
Classifier: Topic :: Software Development :: Libraries :: Python Modules
Classifier: Topic :: System :: Installation/Setup
Classifier: License :: OSI Approved :: BSD License
